README
macspell.py
setup.cfg
setup.py
macspell.egg-info/PKG-INFO
macspell.egg-info/SOURCES.txt
macspell.egg-info/dependency_links.txt
macspell.egg-info/top_level.txt