Metadata-Version: 1.1
Name: macspell
Version: 2017
Summary: MacSpell spell checker
Home-page: http://ruda.github.io/macspell/
Author: Rudá Moura
Author-email: ruda.moura@gmail.com
License: BSD
Keywords: spell checker ispell
Platform: Darwin
Classifier: Programming Language :: Python
Classifier: License :: OSI Approved :: BSD License
Classifier: Environment :: MacOS X
Classifier: Operating System :: MacOS :: MacOS X
Classifier: Topic :: Text Processing
Classifier: Topic :: Text Processing :: Linguistic
Classifier: Topic :: Utilities
